CupDefs/__init__.py
CupDefs/init.py
CupDefs/logger.py
CupDefs/logo
CupDefs/utils.py
CupDefs/vars.py
CupDefs/vergen.py
CupDefs-1.6.dist-info/METADATA
CupDefs-1.6.dist-info/WHEEL
CupDefs-1.6.dist-info/top_level.txt
CupDefs-1.6.dist-info/RECORD
