Metadata-Version: 2.1
Name: CupDefs
Version: 1.6
Author-email: Savtis <nihyisebe@gmail.com>
Classifier: Programming Language :: Python :: 3
Classifier: Operating System :: OS Independent
Requires-Python: >=3.8
Requires-Dist: colorama
